pyurlib/__init__.py
pyurlib/pyurl.py
pyurlib-1.0.dist-info/LICENSE
pyurlib-1.0.dist-info/METADATA
pyurlib-1.0.dist-info/WHEEL
pyurlib-1.0.dist-info/top_level.txt
pyurlib-1.0.dist-info/RECORD
