Metadata-Version: 2.1
Name: pyurlib
Version: 1.0
Summary: Pythonic representation of URLs
Author: Finn Drabsch
Author-email: finndrabsch@gmail.com
Classifier: Programming Language :: Python :: 3
Classifier: License :: OSI Approved :: MIT License
Classifier: Operating System :: OS Independent
Requires-Python: >=3.6
License-File: LICENSE
